outtakes.py
abulafia/__init__.py
abulafia/actions/__init__.py
abulafia/actions/actions.py
abulafia/functions/__init__.py
abulafia/functions/core_functions.py
abulafia/observers/__init__.py
abulafia/observers/observers.py
abulafia/task_specs/__init__.py
abulafia/task_specs/core_task.py
abulafia/task_specs/pipeline.py
abulafia/task_specs/task_specs.py
abulafia-0.2.2.dist-info/LICENSE
abulafia-0.2.2.dist-info/METADATA
abulafia-0.2.2.dist-info/WHEEL
abulafia-0.2.2.dist-info/top_level.txt
abulafia-0.2.2.dist-info/RECORD
