Metadata-Version: 2.1
Name: abulafia
Version: 0.2.2
Summary: A tool for fair and reproducible crowdsourcing using Toloka
Author: Tuomo Hiippala, Helmiina Hotti, Rosa Suviranta
Requires-Python: >=3.8
License-File: LICENSE
Requires-Dist: crowd-kit >=1.2.1
Requires-Dist: pytest
Requires-Dist: PyYAML ==6.0
Requires-Dist: shapely ==2.0.1
Requires-Dist: toloka-kit[pandas] >=1.0.0
Requires-Dist: wasabi ==1.1.1
